iso_dl/__init__.py
iso_dl/__main__.py
iso_dl/cli.py
iso_dl/_distros/__init__.py
iso_dl/_distros/core.py
iso_dl/_distros/distros.py
iso_dl/_distros/utils.py
iso_dl-0.4.2.data/scripts/iso-dl
iso_dl-0.4.2.dist-info/METADATA
iso_dl-0.4.2.dist-info/WHEEL
iso_dl-0.4.2.dist-info/top_level.txt
iso_dl-0.4.2.dist-info/RECORD
